README.rst
setup.py
sanajeh/VERSION
sanajeh/__init__.py
sanajeh/anat.py
sanajeh/bids.py
sanajeh/data.py
sanajeh/files.py
sanajeh/fmri.py
sanajeh/ieeg.py
sanajeh/pipeline.py
sanajeh/simulate_prf.py
sanajeh.egg-info/PKG-INFO
sanajeh.egg-info/SOURCES.txt
sanajeh.egg-info/dependency_links.txt
sanajeh.egg-info/requires.txt
sanajeh.egg-info/top_level.txt
sanajeh/data/electrodes.tsv
sanajeh/data/anat/T1.mgz
sanajeh/data/anat/aparc.a2009s+aseg.mgz